typist-0.0.1.dist-info/RECORD
typist-0.0.1.dist-info/WHEEL
typist-0.0.1.dist-info/metadata.json
typist-0.0.1.dist-info/METADATA
typist-0.0.1.dist-info/top_level.txt
typist-0.0.1.dist-info/pbr.json
typist-0.0.1.dist-info/DESCRIPTION.rst
typist/_docstring.py
typist/__init__.py
typist/_transformer.py
typist/_py.py
typist/_type_check.py
typist/_import_hook.py
typist/tests/__init__.py
