Metadata-Version: 2.0
Name: typist
Version: 0.0.1
Summary: type checking at test time
Home-page: https://github.com/dstanek/typist
Author: David Stanek
Author-email: dstanek@dstanek.com
License: Apache Software License
Platform: UNKNOWN
Classifier: Development Status :: 3 - Alpha
Classifier: Intended Audience :: Developers
Classifier: License :: OSI Approved :: Apache Software License
Classifier: Natural Language :: English
Classifier: Operating System :: OS Independent
Classifier: Programming Language :: Python
Classifier: Topic :: Software Development :: Testing
Requires-Dist: docutils
